{
  "items": [
    {
      "concept": {
        "CONCEPT_CLASS_ID": "Procedure",
        "CONCEPT_CODE": "86273004",
        "CONCEPT_ID": 4311405,
        "CONCEPT_NAME": "Biopsy",
        "DOMAIN_ID": "Procedure",
        "INVALID_REASON": "V",
        "INVALID_REASON_CAPTION": "Valid",
        "STANDARD_CONCEPT": "S",
        "STANDARD_CONCEPT_CAPTION": "Standard",
        "VOCABULARY_ID": "SNOMED",
        "VALID_START_DATE": "2002-01-31",
        "VALID_END_DATE": "2099-12-31"
      },
      "isExcluded": false,
      "includeDescendants": true,
      "includeMapped": false
    },
    {
      "concept": {
        "CONCEPT_CLASS_ID": "Procedure",
        "CONCEPT_CODE": "284401000000107",
        "CONCEPT_ID": 44793508,
        "CONCEPT_NAME": "Radiology procedures",
        "DOMAIN_ID": "Procedure",
        "INVALID_REASON": "V",
        "INVALID_REASON_CAPTION": "Valid",
        "STANDARD_CONCEPT": "S",
        "STANDARD_CONCEPT_CAPTION": "Standard",
        "VOCABULARY_ID": "SNOMED",
        "VALID_START_DATE": "2007-04-02",
        "VALID_END_DATE": "2099-12-31"
      },
      "isExcluded": false,
      "includeDescendants": true,
      "includeMapped": false
    }
  ]
}